lipisha/__init__.py
lipisha/api_config.py
lipisha/lipisha.py
lipisha-0.3.0.dist-info/AUTHORS.rst
lipisha-0.3.0.dist-info/LICENSE
lipisha-0.3.0.dist-info/METADATA
lipisha-0.3.0.dist-info/WHEEL
lipisha-0.3.0.dist-info/top_level.txt
lipisha-0.3.0.dist-info/RECORD
