Metadata-Version: 2.1
Name: lipisha
Version: 0.3.0
Summary: This package provides bindings for the Lipisha Payments API (https://developer.lipisha.com/)
Home-page: https://github.com/lipisha/lipisha-python-sdk
Author: Mũrĩthi Borona
Author-email: tech@lipisha.com
License: MIT
Keywords: lipisha
Platform: UNKNOWN
Classifier: Development Status :: 5 - Production/Stable
Classifier: Intended Audience :: Developers
Classifier: License :: OSI Approved :: MIT License
Classifier: Natural Language :: English
Classifier: Programming Language :: Python :: 2
Classifier: Programming Language :: Python :: 2.6
Classifier: Programming Language :: Python :: 2.7
Classifier: Programming Language :: Python :: 3
Classifier: Programming Language :: Python :: 3.3
Classifier: Programming Language :: Python :: 3.4
Classifier: Programming Language :: Python :: 3.7
Classifier: Programming Language :: Python :: 3.8
Classifier: Topic :: Internet :: WWW/HTTP
